wt_django_tools-1.0.0.dist-info/licenses/LICENSE
wt_tools/__init__.py
wt_tools/_version.py
wt_tools/templatetags/__init__.py
wt_tools/templatetags/pagination_tags.py
wt_django_tools-1.0.0.dist-info/METADATA
wt_django_tools-1.0.0.dist-info/WHEEL
wt_django_tools-1.0.0.dist-info/top_level.txt
wt_django_tools-1.0.0.dist-info/RECORD
