Metadata-Version: 2.4
Name: wt-django-tools
Version: 1.0.0
Summary: A set of tools and abstractions for Django projects.
Author-email: Ian Waldron <maintainers@waldrontech.co>
License-Expression: MIT
Project-URL: Homepage, https://github.com/ian-wt/wt-django-tools
Project-URL: Repository, https://github.com/ian-wt/wt-django-tools
Project-URL: Issues, https://github.com/ian-wt/wt-django-tools/issues
Project-URL: Documentation, https://github.com/ian-wt/wt-django-tools#readme
Keywords: django
Classifier: Development Status :: 5 - Production/Stable
Classifier: Environment :: Web Environment
Classifier: Framework :: Django
Classifier: Framework :: Django :: 4.2
Classifier: Framework :: Django :: 5.0
Classifier: Framework :: Django :: 5.1
Classifier: Framework :: Django :: 5.2
Classifier: Operating System :: OS Independent
Classifier: Programming Language :: Python :: 3
Classifier: Programming Language :: Python :: 3.9
Classifier: Programming Language :: Python :: 3.10
Classifier: Programming Language :: Python :: 3.11
Classifier: Programming Language :: Python :: 3.12
Classifier: Programming Language :: Python :: 3.13
Classifier: Topic :: Internet :: WWW/HTTP
Classifier: Topic :: Internet :: WWW/HTTP :: Dynamic Content
Classifier: Topic :: Software Development :: Libraries :: Python Modules
Requires-Python: >=3.9
License-File: LICENSE
Requires-Dist: django>=4.2
Provides-Extra: dev
Requires-Dist: pytest-django; extra == "dev"
Requires-Dist: pytest-cov; extra == "dev"
Provides-Extra: test
Requires-Dist: pytest-django; extra == "test"
Requires-Dist: pytest-cov; extra == "test"
Dynamic: license-file
